{
  "StyledLayerDescriptor": {
    "$": {
      "version": "1.0.0",
      "xsi:schemaLocation": "http://www.opengis.net/sld StyledLayerDescriptor.xsd",
      "xmlns": "http://www.opengis.net/sld",
      "xmlns:ogc": "http://www.opengis.net/ogc",
      "xmlns:xlink": "http://www.w3.org/1999/xlink",
      "xmlns:xsi": "http://www.w3.org/2001/XMLSchema-instance"
    },
    "NamedLayer": [{
      "Name": [
        "External Graphic"
      ],
      "UserStyle": [{
        "Title": [
          "External Graphic"
        ],
        "FeatureTypeStyle": [{
          "Rule": [{
            "PointSymbolizer": [{
              "Graphic": [{
                "ExternalGraphic": [{
                  "OnlineResource": [{
                    "$": {
                      "xlink:type": "simple",
                      "xmlns:xlink": "http://www.w3.org/1999/xlink",
                      "xlink:href": "https://upload.wikimedia.org/wikipedia/commons/6/67/OpenLayers_logo.svg"
                    }
                  }],
                  "Format": [
                    "image/svg+xml"
                  ]
                }],
                "Size": [
                  "10"
                ],
                "Rotation": [
                  "10"
                ]
              }]
            }]
          }]
        }]
      }]
    }]
  }
}
